<?xml version="1.0" encoding="UTF-8" standalone="yes"?>
<Siri xmlns="http://www.siri.org.uk/siri" xmlns:xsi="http://www.w3.org/2001/XMLSchema-instance" version="2.0" xsi:schemaLocation="http://www.siri.org.uk/siri ../../xsd/siri.xsd"/>
<!--
This example was extracted on May 25th from the DDS FISZ.
Content wrapped in a comment because of validation errors causing travis to fail

<Siri xmlns="http://www.siri.org.uk/siri" xmlns:acsb="http://www.ifopt.org.uk/acsb" xmlns:ifopt="http://www.ifopt.org.uk/ifopt" xmlns:vdv="www.vdv.de/siri/extensions/sx" xmlns:xsi="http://www.w3.org/2001/XMLSchema-instance" version="2.0">
<ServiceDelivery>
<ResponseTimestamp>2020-03-08T14:45:40+01:00</ResponseTimestamp>
<ProducerRef>dds_ems_siri-test</ProducerRef>
<Status>true</Status>
<SituationExchangeDelivery>
<ResponseTimestamp>2020-03-08T14:45:40+01:00</ResponseTimestamp>
<SubscriptionRef>rJZZdSxMB8</SubscriptionRef>
<Situations>

<PtSituationElement>
 <CreationTime>2020-03-02T18:08:33+01:00</CreationTime>
 <SituationNumber>5e2e8d12866cda0c44d93bfe</SituationNumber>
 <Version>1</Version>
 <Source>
  <SourceType>directReport</SourceType>
 </Source>
 <ValidityPeriod>
  <StartTime>2020-01-27T08:11:00+01:00</StartTime>
  <EndTime>2020-04-01T23:59:00+02:00</EndTime>
 </ValidityPeriod>
 <MiscellaneousReason>specialType</MiscellaneousReason>
 <ReportType>incident</ReportType>
 <PublishingActions>
  <Extensions>
   <vdv:PassengerInformationAction>
	<vdv:ActionRef>5e2e8d12866cda0c44d93bfe</vdv:ActionRef>
	<vdv:RecordedAtTime>2020-03-02T18:08:33+01:00</vdv:RecordedAtTime>
	<vdv:Version>1</vdv:Version>
	<vdv:SourceRef>820</vdv:SourceRef>
	<vdv:OverallValidityPeriod>
	 <StartTime>2020-01-27T08:11:00+01:00</StartTime>
	 <EndTime>2020-04-01T23:59:00+02:00</EndTime>
	</vdv:OverallValidityPeriod>
	<vdv:TextualContent>
	 <Summary>Bauarbeiten Schlösslistrasse Ebikon: Die Haltestelle Gerbe in Fahrtrichtung Unterlöchli kann nicht bedient werden. Bitte Ersatzhaltestellen benutzen.</Summary>
	 <Description>Bauarbeiten Schlösslistrasse Ebikon: Die Haltestelle Gerbe in Fahrtrichtung Unterlöchli kann nicht bedient werden. Bitte Ersatzhaltestellen benutzen.</Description>
	</vdv:TextualContent>
	<vdv:PublishAtScope>
	 <Operators>
	  <AffectedOperator>
	   <OperatorRef>85:820</OperatorRef>
	  </AffectedOperator>
	 </Operators>
	 <StopPoints>
	  <AffectedStopPoint>
	   <StopPointRef>858965900</StopPointRef>
	  </AffectedStopPoint>
	  <AffectedStopPoint>
	   <StopPointRef>858965901</StopPointRef>
	  </AffectedStopPoint>
	  <AffectedStopPoint>
	   <StopPointRef>858965902</StopPointRef>
	  </AffectedStopPoint>
	  <AffectedStopPoint>
	   <StopPointRef>858966800</StopPointRef>
	  </AffectedStopPoint>
	  <AffectedStopPoint>
	   <StopPointRef>858966801</StopPointRef>
	  </AffectedStopPoint>
	  <AffectedStopPoint>
	   <StopPointRef>858966802</StopPointRef>
	  </AffectedStopPoint>
	 </StopPoints>
	</vdv:PublishAtScope>
   </vdv:PassengerInformationAction>
  </Extensions>
 </PublishingActions>
</PtSituationElement>

 </Situations>
</SituationExchangeDelivery>
</ServiceDelivery>
</Siri>
-->
